MANIFEST.in
distribute_setup.py
setup.cfg
setup.py
python_webnews.egg-info/PKG-INFO
python_webnews.egg-info/SOURCES.txt
python_webnews.egg-info/dependency_links.txt
python_webnews.egg-info/not-zip-safe
python_webnews.egg-info/top_level.txt
tests/__init__.py
tests/test_API.py
tests/test_webnewsObject.py
webnews/__init__.py
webnews/api.py
webnews/webnews.py