Metadata-Version: 1.0
Name: python-webnews
Version: 0.1.0
Summary: CSH webnews library
Home-page: https://github.com/AndrewHanes/Python-Webnews
Author: ahanes
Author-email: ahanes@csh.rit.edu
License: None
Keywords: csh webnews
Platform: UNKNOWN
